nisqa/NISQA_lib.py
nisqa/NISQA_model.py
nisqa/__init__.py
nisqa-2.0.post2.dist-info/LICENSE
nisqa-2.0.post2.dist-info/METADATA
nisqa-2.0.post2.dist-info/WHEEL
nisqa-2.0.post2.dist-info/top_level.txt
nisqa-2.0.post2.dist-info/RECORD
