Metadata-Version: 2.1
Name: nisqa
Version: 2.0.post2
Summary: NISQA - Non-Intrusive Speech Quality and TTS Naturalness Assessment
Project-URL: Homepage, https://github.com/gabrielmittag/NISQA
Project-URL: Issues, https://github.com/gabrielmittag/NISQA/issues
Classifier: Programming Language :: Python :: 3
Classifier: License :: OSI Approved :: MIT License
Classifier: Operating System :: OS Independent
Requires-Python: >=3.9
License-File: LICENSE
Requires-Dist: pillow ==10.2.0
Requires-Dist: torch ==2.2.1
Requires-Dist: scipy ==1.12.0
Requires-Dist: torchvision ==0.17.1
Requires-Dist: librosa ==0.10.1
Requires-Dist: matplotlib ==3.8.3
Requires-Dist: numba ==0.59.0
Requires-Dist: numpy ==1.26.4
Requires-Dist: pandas ==2.2.1
Requires-Dist: pyyaml ==6.0.1
Requires-Dist: scikit-learn ==1.4.1.post1
Requires-Dist: seaborn ==0.13.2
Requires-Dist: tqdm ==4.66.2
